odoo/addons/purchase_lot/README.rst
odoo/addons/purchase_lot/__init__.py
odoo/addons/purchase_lot/__manifest__.py
odoo/addons/purchase_lot/i18n/es.po
odoo/addons/purchase_lot/i18n/it.po
odoo/addons/purchase_lot/i18n/purchase_lot.pot
odoo/addons/purchase_lot/models/__init__.py
odoo/addons/purchase_lot/models/purchase_order_line.py
odoo/addons/purchase_lot/models/stock_rule.py
odoo/addons/purchase_lot/readme/CONTRIBUTORS.rst
odoo/addons/purchase_lot/readme/DESCRIPTION.rst
odoo/addons/purchase_lot/static/description/icon.png
odoo/addons/purchase_lot/static/description/index.html
odoo/addons/purchase_lot/tests/__init__.py
odoo/addons/purchase_lot/tests/test_purchase_lot.py
odoo/addons/purchase_lot/views/purchase_order_view.xml
odoo14_addon_purchase_lot-14.0.1.0.1.dev9.dist-info/METADATA
odoo14_addon_purchase_lot-14.0.1.0.1.dev9.dist-info/WHEEL
odoo14_addon_purchase_lot-14.0.1.0.1.dev9.dist-info/top_level.txt
odoo14_addon_purchase_lot-14.0.1.0.1.dev9.dist-info/RECORD
